skill_fallback_unknown/LICENSE
skill_fallback_unknown/LICENSE.md
skill_fallback_unknown/README.md
skill_fallback_unknown/__init__.py
skill_fallback_unknown/skill.json
skill_fallback_unknown/version.py
skill_fallback_unknown/dialog/ca-es/question.dialog
skill_fallback_unknown/dialog/ca-es/unknown.dialog
skill_fallback_unknown/dialog/ca-es/who.is.dialog
skill_fallback_unknown/dialog/ca-es/why.is.dialog
skill_fallback_unknown/dialog/cs-cz/question.dialog
skill_fallback_unknown/dialog/cs-cz/unknown.dialog
skill_fallback_unknown/dialog/cs-cz/who.is.dialog
skill_fallback_unknown/dialog/cs-cz/why.is.dialog
skill_fallback_unknown/dialog/da-dk/question.dialog
skill_fallback_unknown/dialog/da-dk/unknown.dialog
skill_fallback_unknown/dialog/da-dk/who.is.dialog
skill_fallback_unknown/dialog/da-dk/why.is.dialog
skill_fallback_unknown/dialog/de-de/question.dialog
skill_fallback_unknown/dialog/de-de/unknown.dialog
skill_fallback_unknown/dialog/de-de/who.is.dialog
skill_fallback_unknown/dialog/de-de/why.is.dialog
skill_fallback_unknown/dialog/en-us/question.dialog
skill_fallback_unknown/dialog/en-us/unknown.dialog
skill_fallback_unknown/dialog/en-us/websearch.dialog
skill_fallback_unknown/dialog/en-us/who.is.dialog
skill_fallback_unknown/dialog/en-us/why.is.dialog
skill_fallback_unknown/dialog/es-es/question.dialog
skill_fallback_unknown/dialog/es-es/unknown.dialog
skill_fallback_unknown/dialog/es-es/who.is.dialog
skill_fallback_unknown/dialog/es-es/why.is.dialog
skill_fallback_unknown/dialog/es-lm/question.dialog
skill_fallback_unknown/dialog/es-lm/unknown.dialog
skill_fallback_unknown/dialog/es-lm/who.is.dialog
skill_fallback_unknown/dialog/es-lm/why.is.dialog
skill_fallback_unknown/dialog/eu-eu/question.dialog
skill_fallback_unknown/dialog/eu-eu/unknown.dialog
skill_fallback_unknown/dialog/eu-eu/who.is.dialog
skill_fallback_unknown/dialog/eu-eu/why.is.dialog
skill_fallback_unknown/dialog/fa-fa/question.dialog
skill_fallback_unknown/dialog/fa-fa/unknown.dialog
skill_fallback_unknown/neon_skill_fallback_unknown.egg-info/PKG-INFO
skill_fallback_unknown/neon_skill_fallback_unknown.egg-info/SOURCES.txt
skill_fallback_unknown/neon_skill_fallback_unknown.egg-info/dependency_links.txt
skill_fallback_unknown/neon_skill_fallback_unknown.egg-info/entry_points.txt
skill_fallback_unknown/neon_skill_fallback_unknown.egg-info/requires.txt
skill_fallback_unknown/neon_skill_fallback_unknown.egg-info/top_level.txt
neon_skill_fallback_unknown-2.0.2.dist-info/LICENSE
neon_skill_fallback_unknown-2.0.2.dist-info/LICENSE.md
neon_skill_fallback_unknown-2.0.2.dist-info/METADATA
neon_skill_fallback_unknown-2.0.2.dist-info/WHEEL
neon_skill_fallback_unknown-2.0.2.dist-info/entry_points.txt
neon_skill_fallback_unknown-2.0.2.dist-info/top_level.txt
neon_skill_fallback_unknown-2.0.2.dist-info/RECORD
