Metadata-Version: 2.1
Name: neon-skill-fallback-unknown
Version: 2.0.2
Summary: Neon Unknown Fallback Skill
Home-page: https://github.com/NeonGeckoCom/skill-fallback_unknown
Author: Neongecko
Author-email: developers@neon.ai
License: BSD-3-Clause
License-File: LICENSE
License-File: LICENSE.md
Requires-Dist: neon-utils~=1.5
Requires-Dist: ovos-utils>=0.0.28,~=0.0
Requires-Dist: ovos-bus-client>=0.0.3,~=0.0
Requires-Dist: ovos-workshop>=0.0.15,~=0.0
Provides-Extra: test
Requires-Dist: neon-minerva~=0.1; extra == "test"
